setup.py
wormhole/__init__.py
wormhole/client.py
wormhole/server.py
wormhole.egg-info/PKG-INFO
wormhole.egg-info/SOURCES.txt
wormhole.egg-info/dependency_links.txt
wormhole.egg-info/top_level.txt