Metadata-Version: 1.0
Name: wormhole
Version: 0.0.1
Summary: RPC
Home-page: http://www.github.com/wmttom/wormhole
Author: Tom
Author-email: UNKNOWN
License: MIT
Platform: UNKNOWN
